setup.py
PSI_Reader/PSI_data.py
PSI_Reader/PSI_package.py
PSI_Reader/PSI_tiff.py
PSI_Reader/__init__.py
PSI_Reader.egg-info/PKG-INFO
PSI_Reader.egg-info/SOURCES.txt
PSI_Reader.egg-info/dependency_links.txt
PSI_Reader.egg-info/not-zip-safe
PSI_Reader.egg-info/top_level.txt