Metadata-Version: 1.0
Name: PSI-Reader
Version: 0.1
Summary: TIFF FILE READER_
Home-page: UNKNOWN
Author: alex
Author-email: alex@parkafm.co.kr
License: UNKNOWN
Platform: UNKNOWN
